quinine/__init__.py
quinine/quinfig.py
quinine/common/argparse.py
quinine/common/cerberus.py
quinine/common/gin.py
quinine/common/sweep.py
quinine/common/utils.py
quinine-0.3.0.dist-info/LICENSE
quinine-0.3.0.dist-info/METADATA
quinine-0.3.0.dist-info/WHEEL
quinine-0.3.0.dist-info/top_level.txt
quinine-0.3.0.dist-info/RECORD
