Metadata-Version: 2.1
Name: quinine
Version: 0.3.0
Summary: quinine is a library for configuring machine learning projects.
Home-page: UNKNOWN
Author: Karan Goel
Author-email: kgoel93@gmail.com
License: MIT
Keywords: configuration yaml machine learning ml ai nlp cv vision deep learning
Platform: UNKNOWN
Requires-Dist: Cerberus (==1.3.2)
Requires-Dist: pyyaml (==5.4)
Requires-Dist: cytoolz (==0.11.0)
Requires-Dist: funcy (==1.15)
Requires-Dist: gin-config (==0.3.0)
Requires-Dist: munch (==2.5.0)
Requires-Dist: toposort (==1.5)
